[
    {
        "actual": -3.4,
        "country": "Australia",
        "currency": "AUD",
        "name": "New Motor Vehicle Sales (MoM)",
        "previous": 3.1,
        "timestamp": 1266798600,
        "volatility": 0
    },
    {
        "actual": 5.8,
        "country": "Thailand",
        "currency": "THB",
        "forecast": 3.1,
        "name": "GDP (YoY)",
        "previous": -2.8,
        "timestamp": 1266805800,
        "volatility": 1
    },
    {
        "actual": 9.2,
        "country": "Taiwan",
        "currency": "TWD",
        "forecast": 8.4,
        "name": "GDP (YoY)",
        "previous": -1.3,
        "timestamp": 1266816600,
        "volatility": 0
    },
    {
        "actual": -2.3,
        "country": "Mexico",
        "currency": "MXN",
        "forecast": -2.5,
        "name": "GDP (YoY)",
        "previous": -6.2,
        "timestamp": 1266847200,
        "volatility": 1
    },
    {
        "actual": 8.4,
        "country": "Argentina",
        "currency": "ARS",
        "forecast": 8.4,
        "name": "Unemployment Rate",
        "previous": 9.1,
        "timestamp": 1266865200,
        "volatility": 0
    },
    {
        "country": "Japan",
        "currency": "JPY",
        "name": "Monetary Policy Meeting Minutes",
        "timestamp": 1266882600,
        "volatility": 1
    }
]
