[
    {
        "actual": 5.7,
        "country": "Singapore",
        "currency": "SGD",
        "forecast": 2.1,
        "name": "GDP (QoQ) (Q4)",
        "previous": 1.9,
        "timestamp": 1452124800,
        "volatility": 0
    },
    {
        "actual": -12.7,
        "country": "Australia",
        "currency": "AUD",
        "forecast": -3.0,
        "name": "Building Approvals (MoM) (Nov)",
        "previous": 3.3,
        "timestamp": 1452126600,
        "volatility": 1
    },
    {
        "actual": 1.0,
        "country": "Australia",
        "currency": "AUD",
        "name": "Exports (MoM) (Nov)",
        "previous": -3.0,
        "timestamp": 1452126600,
        "volatility": 0
    },
    {
        "actual": -1.0,
        "country": "Australia",
        "currency": "AUD",
        "name": "Imports (MoM) (Nov)",
        "previous": 0.0,
        "timestamp": 1452126600,
        "volatility": 0
    },
    {
        "actual": -0.5,
        "country": "Australia",
        "currency": "AUD",
        "name": "Private House Approvals (Nov)",
        "previous": -2.0,
        "timestamp": 1452126600,
        "volatility": 0
    },
    {
        "actual": -2.906,
        "country": "Australia",
        "currency": "AUD",
        "forecast": -3.1,
        "name": "Trade Balance (Nov)",
        "previous": -3.247,
        "timestamp": 1452126600,
        "volatility": 1
    },
    {
        "actual": 1.224,
        "country": "Japan",
        "currency": "JPY",
        "name": "30-Year JGB Auction",
        "previous": 1.397,
        "timestamp": 1452138300,
        "volatility": 0
    },
    {
        "actual": 76.1,
        "country": "Thailand",
        "currency": "THB",
        "name": "Consumer Confidence (Dec)",
        "previous": 74.6,
        "timestamp": 1452139200,
        "volatility": 0
    },
    {
        "actual": 6.3,
        "country": "Malaysia",
        "currency": "MYR",
        "forecast": 12.2,
        "name": "Exports (YoY) (Nov)",
        "previous": 16.7,
        "timestamp": 1452139200,
        "volatility": 0
    },
    {
        "actual": 9.1,
        "country": "Malaysia",
        "currency": "MYR",
        "forecast": 14.1,
        "name": "Imports (YoY) (Nov)",
        "previous": -0.4,
        "timestamp": 1452139200,
        "volatility": 0
    },
    {
        "actual": 10.23,
        "country": "Malaysia",
        "currency": "MYR",
        "forecast": 12.0,
        "name": "Trade Balance (Nov)",
        "previous": 12.16,
        "timestamp": 1452139200,
        "volatility": 0
    },
    {
        "actual": 0.7,
        "country": "Netherlands",
        "currency": "EUR",
        "name": "Dutch CPI (YoY)",
        "previous": 0.6,
        "timestamp": 1452144600,
        "volatility": 0
    },
    {
        "actual": 54.4,
        "country": "Saudi Arabia",
        "currency": "SAR",
        "name": "Markit Composite PMI (Dec)",
        "previous": 56.3,
        "timestamp": 1452144600,
        "volatility": 0
    },
    {
        "actual": 53.3,
        "country": "United Arab Emirates",
        "currency": "AED",
        "name": "Markit Composite PMI (Dec)",
        "previous": 54.5,
        "timestamp": 1452144600,
        "volatility": 0
    },
    {
        "actual": 1.5,
        "country": "Germany",
        "currency": "EUR",
        "forecast": 0.1,
        "name": "German Factory Orders (MoM) (Nov)",
        "previous": 1.7,
        "timestamp": 1452150000,
        "volatility": 1
    },
    {
        "actual": 0.2,
        "country": "Germany",
        "currency": "EUR",
        "forecast": 0.5,
        "name": "German Retail Sales (MoM) (Nov)",
        "previous": -0.1,
        "timestamp": 1452150000,
        "volatility": 1
    },
    {
        "actual": 2.3,
        "country": "Germany",
        "currency": "EUR",
        "forecast": 2.4,
        "name": "German Retail Sales (YoY) (Nov)",
        "previous": 2.5,
        "timestamp": 1452150000,
        "volatility": 0
    },
    {
        "actual": 0.82,
        "country": "Brazil",
        "currency": "BRL",
        "forecast": 0.9,
        "name": "IPC-Fipe Inflation Index (MoM) (Dec)",
        "previous": 1.06,
        "timestamp": 1452150000,
        "volatility": 1
    },
    {
        "actual": -0.24,
        "country": "Finland",
        "currency": "EUR",
        "name": "Finnish Trade Balance (Nov)",
        "previous": -0.16,
        "timestamp": 1452150000,
        "volatility": 0
    },
    {
        "actual": 58.0,
        "country": "Sweden",
        "currency": "SEK",
        "name": "Services PMI (MoM) (Dec)",
        "previous": 56.3,
        "timestamp": 1452151800,
        "volatility": 0
    },
    {
        "actual": 80.61,
        "country": "Philippines",
        "currency": "PHP",
        "name": "FX Reserves USD (Dec)",
        "previous": 80.17,
        "timestamp": 1452153360,
        "volatility": 0
    },
    {
        "actual": 9.5,
        "country": "United Kingdom",
        "currency": "GBP",
        "forecast": 9.0,
        "name": "Halifax House Price Index (YoY) (Dec)",
        "previous": 9.0,
        "timestamp": 1452153600,
        "volatility": 1
    },
    {
        "actual": 1.7,
        "country": "United Kingdom",
        "currency": "GBP",
        "forecast": 0.5,
        "name": "Halifax House Price Index (MoM) (Dec)",
        "previous": 0.0,
        "timestamp": 1452153600,
        "volatility": 1
    },
    {
        "actual": 3.7,
        "country": "Denmark",
        "currency": "DKK",
        "name": "Unemployment Rate (Nov)",
        "previous": 3.8,
        "timestamp": 1452153600,
        "volatility": 0
    },
    {
        "actual": -1.6,
        "country": "Austria",
        "currency": "EUR",
        "name": "Austrian Wholesale Prices n.s.a (MoM) (Dec)",
        "previous": -0.3,
        "timestamp": 1452153600,
        "volatility": 0
    },
    {
        "actual": -3.0,
        "country": "Austria",
        "currency": "EUR",
        "name": "Austrian Wholesale Prices n.s.a (YoY) (Dec)",
        "previous": -3.5,
        "timestamp": 1452153600,
        "volatility": 0
    },
    {
        "actual": 4.4,
        "country": "Hungary",
        "currency": "HUF",
        "name": "Retail Sales (YoY) (Nov)",
        "previous": 4.6,
        "timestamp": 1452153600,
        "volatility": 0
    },
    {
        "actual": 358.8,
        "country": "Hong Kong",
        "currency": "HKD",
        "name": "Foreign Reserves (USD) (Dec)",
        "previous": 355.8,
        "timestamp": 1452155400,
        "volatility": 0
    },
    {
        "actual": 11.3,
        "country": "Italy",
        "currency": "EUR",
        "forecast": 11.5,
        "name": "Italian Monthly Unemployment Rate (Nov)",
        "previous": 11.5,
        "timestamp": 1452157200,
        "volatility": 0
    },
    {
        "actual": 247.7,
        "country": "Singapore",
        "currency": "SGD",
        "name": "Foreign Reserves USD (MoM) (Dec)",
        "previous": 247.1,
        "timestamp": 1452157200,
        "volatility": 0
    },
    {
        "actual": 59.51,
        "country": "Czech Republic",
        "currency": "CZK",
        "name": "FX Reserves (EUR) (Dec)",
        "previous": 58.84,
        "timestamp": 1452157200,
        "volatility": 0
    },
    {
        "actual": 49.0,
        "country": "Euro Zone",
        "currency": "EUR",
        "name": "Retail PMI",
        "previous": 48.5,
        "timestamp": 1452157800,
        "volatility": 0
    },
    {
        "actual": 79.6,
        "country": "South Africa",
        "currency": "ZAR",
        "name": "Business Confidence (Dec)",
        "previous": 82.7,
        "timestamp": 1452159000,
        "volatility": 0
    },
    {
        "actual": 9.2,
        "country": "Indonesia",
        "currency": "IDR",
        "name": "M2 Money Supply (YoY) (Nov)",
        "previous": 10.4,
        "timestamp": 1452160080,
        "volatility": 0
    },
    {
        "actual": 0.86,
        "country": "France",
        "currency": "EUR",
        "name": "French 10-Year OAT Auction",
        "previous": 0.95,
        "timestamp": 1452160800,
        "volatility": 0
    },
    {
        "actual": 1.44,
        "country": "France",
        "currency": "EUR",
        "name": "French 15-Year OAT Auction",
        "previous": 1.49,
        "timestamp": 1452160800,
        "volatility": 0
    },
    {
        "actual": 0.44,
        "country": "Brazil",
        "currency": "BRL",
        "forecast": 0.43,
        "name": "IGP-DI Inflation Index (MoM) (Dec)",
        "previous": 1.19,
        "timestamp": 1452160800,
        "volatility": 0
    },
    {
        "actual": 95.3,
        "country": "Malaysia",
        "currency": "MYR",
        "name": "FX Reserves USD",
        "previous": 94.9,
        "timestamp": 1452160800,
        "volatility": 0
    },
    {
        "actual": 24.5,
        "country": "Greece",
        "currency": "EUR",
        "name": "Greek Unemployment Rate (Oct)",
        "previous": 24.6,
        "timestamp": 1452160800,
        "volatility": 0
    },
    {
        "actual": 106.8,
        "country": "Euro Zone",
        "currency": "EUR",
        "forecast": 106.1,
        "name": "Business and Consumer Survey (Dec)",
        "previous": 106.1,
        "timestamp": 1452160800,
        "volatility": 0
    },
    {
        "actual": 0.4,
        "country": "Euro Zone",
        "currency": "EUR",
        "forecast": 0.4,
        "name": "Business Climate (Dec)",
        "previous": 0.4,
        "timestamp": 1452160800,
        "volatility": 0
    },
    {
        "actual": -6.0,
        "country": "Euro Zone",
        "currency": "EUR",
        "forecast": -6.0,
        "name": "Consumer Confidence (Dec)",
        "previous": -5.9,
        "timestamp": 1452160800,
        "volatility": 0
    },
    {
        "actual": 3.6,
        "country": "Euro Zone",
        "currency": "EUR",
        "name": "Consumer Inflation Expectation (Dec)",
        "previous": 3.7,
        "timestamp": 1452160800,
        "volatility": 0
    },
    {
        "actual": -3.0,
        "country": "Euro Zone",
        "currency": "EUR",
        "name": "Selling Price Expectations (Dec)",
        "previous": -0.7,
        "timestamp": 1452160800,
        "volatility": 0
    },
    {
        "actual": 13.0,
        "country": "Euro Zone",
        "currency": "EUR",
        "forecast": 13.0,
        "name": "Services Sentiment (Dec)",
        "previous": 12.8,
        "timestamp": 1452160800,
        "volatility": 0
    },
    {
        "actual": -2.0,
        "country": "Euro Zone",
        "currency": "EUR",
        "forecast": -3.0,
        "name": "Industrial Sentiment (Dec)",
        "previous": -3.2,
        "timestamp": 1452160800,
        "volatility": 0
    },
    {
        "actual": -0.3,
        "country": "Euro Zone",
        "currency": "EUR",
        "forecast": 0.2,
        "name": "Retail Sales (MoM) (Nov)",
        "previous": -0.2,
        "timestamp": 1452160800,
        "volatility": 1
    },
    {
        "actual": 1.4,
        "country": "Euro Zone",
        "currency": "EUR",
        "forecast": 2.0,
        "name": "Retail Sales (YoY) (Nov)",
        "previous": 2.4,
        "timestamp": 1452160800,
        "volatility": 0
    },
    {
        "actual": 10.5,
        "country": "Euro Zone",
        "currency": "EUR",
        "forecast": 10.7,
        "name": "Unemployment Rate (Dec)",
        "previous": 10.6,
        "timestamp": 1452160800,
        "volatility": 1
    },
    {
        "actual": 2.4,
        "country": "Spain",
        "currency": "EUR",
        "name": "Spanish Business Confidence",
        "previous": -2.7,
        "timestamp": 1452162600,
        "volatility": 0
    },
    {
        "actual": 1.75,
        "country": "Romania",
        "currency": "RON",
        "forecast": 1.75,
        "name": "Interest Rate Decision",
        "previous": 1.75,
        "timestamp": 1452162600,
        "volatility": 0
    },
    {
        "actual": -2.4,
        "country": "Brazil",
        "currency": "BRL",
        "forecast": -1.0,
        "name": "Industrial Production (MoM) (Nov)",
        "previous": -0.6,
        "timestamp": 1452164400,
        "volatility": 0
    },
    {
        "actual": -12.4,
        "country": "Brazil",
        "currency": "BRL",
        "forecast": -10.3,
        "name": "Industrial Production (YoY) (Nov)",
        "previous": -11.1,
        "timestamp": 1452164400,
        "volatility": 1
    },
    {
        "actual": 2.0,
        "country": "Chile",
        "currency": "CLP",
        "name": "Copper Exports (USD) (Dec)",
        "previous": 2.0,
        "timestamp": 1452166200,
        "volatility": 0
    },
    {
        "actual": 5.0,
        "country": "Chile",
        "currency": "CLP",
        "name": "Exports (USD) (Dec)",
        "previous": 5.0,
        "timestamp": 1452166200,
        "volatility": 0
    },
    {
        "actual": 5.0,
        "country": "Chile",
        "currency": "CLP",
        "name": "Imports (USD) (Dec)",
        "previous": 5.0,
        "timestamp": 1452166200,
        "volatility": 0
    },
    {
        "actual": -0.15,
        "country": "Chile",
        "currency": "CLP",
        "forecast": 0.4,
        "name": "Trade Balance (Dec)",
        "previous": -0.17,
        "timestamp": 1452166200,
        "volatility": 0
    },
    {
        "actual": -27.6,
        "country": "United States",
        "currency": "USD",
        "name": "Challenger Job Cuts (YoY)",
        "previous": -13.9,
        "timestamp": 1452169800,
        "volatility": 0
    },
    {
        "actual": 23.6,
        "country": "United States",
        "currency": "USD",
        "name": "Challenger Job Cuts (Dec)",
        "previous": 31.0,
        "timestamp": 1452169800,
        "volatility": 0
    },
    {
        "actual": 90.623,
        "country": "Israel",
        "currency": "ILS",
        "name": "FX Reserve - USD (Dec)",
        "previous": 88.822,
        "timestamp": 1452169800,
        "volatility": 0
    },
    {
        "actual": -18.4,
        "country": "Brazil",
        "currency": "BRL",
        "name": "Auto Production (MoM) (Dec)",
        "previous": -14.2,
        "timestamp": 1452169800,
        "volatility": 0
    },
    {
        "actual": 16.7,
        "country": "Brazil",
        "currency": "BRL",
        "name": "Auto Sales (MoM) (Dec)",
        "previous": 1.6,
        "timestamp": 1452169800,
        "volatility": 0
    },
    {
        "actual": 86.8,
        "country": "Poland",
        "currency": "PLN",
        "name": "FX Reserves (EUR) (Dec)",
        "previous": 92.6,
        "timestamp": 1452171600,
        "volatility": 0
    },
    {
        "country": "Canada",
        "currency": "CAD",
        "name": "BoC Gov Poloz Speaks",
        "timestamp": 1452172200,
        "volatility": 2
    },
    {
        "actual": -4.2,
        "country": "South Africa",
        "currency": "ZAR",
        "name": "Total Vehicle Sales (YoY) (Dec)",
        "previous": 0.4,
        "timestamp": 1452172320,
        "volatility": 0
    },
    {
        "actual": 49.25,
        "country": "South Africa",
        "currency": "ZAR",
        "name": "Total Vehicle Sales (Dec)",
        "previous": 51.26,
        "timestamp": 1452172320,
        "volatility": 0
    },
    {
        "actual": 2.0,
        "country": "United States",
        "currency": "USD",
        "forecast": 2.0,
        "name": "Continuing Jobless Claims",
        "previous": 2.0,
        "timestamp": 1452173400,
        "volatility": 0
    },
    {
        "actual": 277.0,
        "country": "United States",
        "currency": "USD",
        "forecast": 275.0,
        "name": "Initial Jobless Claims",
        "previous": 287.0,
        "timestamp": 1452173400,
        "volatility": 1
    },
    {
        "actual": 275.75,
        "country": "United States",
        "currency": "USD",
        "name": "Jobless Claims 4-Week Avg.",
        "previous": 277.0,
        "timestamp": 1452173400,
        "volatility": 0
    },
    {
        "actual": 0.31,
        "country": "Mexico",
        "currency": "MXN",
        "forecast": 0.34,
        "name": "Core CPI (MoM) (Dec)",
        "previous": 0.04,
        "timestamp": 1452175200,
        "volatility": 0
    },
    {
        "actual": 0.41,
        "country": "Mexico",
        "currency": "MXN",
        "forecast": 0.35,
        "name": "CPI (MoM) (Dec)",
        "previous": 0.55,
        "timestamp": 1452175200,
        "volatility": 1
    },
    {
        "actual": 2.13,
        "country": "Mexico",
        "currency": "MXN",
        "forecast": 2.08,
        "name": "CPI (YoY) (Dec)",
        "previous": 2.21,
        "timestamp": 1452175200,
        "volatility": 1
    },
    {
        "actual": 44.2,
        "country": "United States",
        "currency": "USD",
        "name": "Bloomberg Consumer Confidence",
        "previous": 43.6,
        "timestamp": 1452178200,
        "volatility": 0
    },
    {
        "actual": 42.5,
        "country": "Canada",
        "currency": "CAD",
        "name": "Ivey PMI n.s.a (Dec)",
        "previous": 57.9,
        "timestamp": 1452178800,
        "volatility": 0
    },
    {
        "actual": 49.9,
        "country": "Canada",
        "currency": "CAD",
        "forecast": 56.7,
        "name": "Ivey PMI (Dec)",
        "previous": 63.6,
        "timestamp": 1452178800,
        "volatility": 2
    },
    {
        "actual": -113.0,
        "country": "United States",
        "currency": "USD",
        "forecast": -99.0,
        "name": "Natural Gas Storage",
        "previous": -58.0,
        "timestamp": 1452180600,
        "volatility": 0
    },
    {
        "country": "United States",
        "currency": "USD",
        "name": "Chicago Fed President Evans Speaks",
        "timestamp": 1452201300,
        "volatility": 0
    },
    {
        "actual": 46.8,
        "country": "Australia",
        "currency": "AUD",
        "name": "AIG Construction Index (Dec)",
        "previous": 50.7,
        "timestamp": 1452205800,
        "volatility": 0
    },
    {
        "actual": 1.0,
        "country": "Japan",
        "currency": "JPY",
        "name": "Foreign Reserves (USD) (Dec)",
        "previous": 1.0,
        "timestamp": 1452210600,
        "volatility": 0
    }
]
