[
    {
        "actual": -10.2,
        "country": "South Korea",
        "currency": "KRW",
        "forecast": -4.6,
        "name": "Exports (YoY) (Jul)",
        "previous": -2.7,
        "timestamp": 1470009600,
        "volatility": 0
    },
    {
        "actual": -14.0,
        "country": "South Korea",
        "currency": "KRW",
        "forecast": -9.5,
        "name": "Imports (YoY) (Jul)",
        "previous": -7.7,
        "timestamp": 1470009600,
        "volatility": 0
    },
    {
        "actual": 7.8,
        "country": "South Korea",
        "currency": "KRW",
        "forecast": 9.6,
        "name": "Trade Balance (Jul)",
        "previous": 11.5,
        "timestamp": 1470009600,
        "volatility": 0
    },
    {
        "actual": 8.2,
        "country": "Australia",
        "currency": "AUD",
        "name": "HIA New Home Sales (MoM) (Jun)",
        "previous": -4.4,
        "timestamp": 1470013200,
        "volatility": 1
    },
    {
        "actual": -0.3,
        "country": "Australia",
        "currency": "AUD",
        "name": "MI Inflation Gauge (MoM) (Jul)",
        "previous": 0.6,
        "timestamp": 1470013200,
        "volatility": 0
    },
    {
        "actual": 49.9,
        "country": "China",
        "currency": "CNY",
        "forecast": 50.0,
        "name": "Manufacturing PMI (Jul)",
        "previous": 50.0,
        "timestamp": 1470013200,
        "volatility": 2
    },
    {
        "actual": 53.9,
        "country": "China",
        "currency": "CNY",
        "name": "Non-Manufacturing PMI (Jul)",
        "previous": 53.7,
        "timestamp": 1470013200,
        "volatility": 1
    },
    {
        "country": "United States",
        "currency": "USD",
        "name": "FOMC Member Dudley Speaks",
        "timestamp": 1470014100,
        "volatility": 1
    },
    {
        "actual": 50.1,
        "country": "South Korea",
        "currency": "KRW",
        "name": "Nikkei Manufacturing PMI (Jul)",
        "previous": 50.5,
        "timestamp": 1470015000,
        "volatility": 0
    },
    {
        "actual": 50.6,
        "country": "China",
        "currency": "CNY",
        "forecast": 48.7,
        "name": "Caixin Manufacturing PMI (Jul)",
        "previous": 48.6,
        "timestamp": 1470015900,
        "volatility": 2
    },
    {
        "actual": 49.3,
        "country": "Japan",
        "currency": "JPY",
        "forecast": 49.0,
        "name": "Manufacturing PMI (Jul)",
        "previous": 49.0,
        "timestamp": 1470016800,
        "volatility": 0
    },
    {
        "actual": 51.0,
        "country": "Taiwan",
        "currency": "TWD",
        "name": "Manufacturing PMI (Jul)",
        "previous": 50.5,
        "timestamp": 1470018600,
        "volatility": 0
    },
    {
        "actual": 48.4,
        "country": "Indonesia",
        "currency": "IDR",
        "name": "Nikkei Manufacturing PMI (Jul)",
        "previous": 51.9,
        "timestamp": 1470020400,
        "volatility": 0
    },
    {
        "actual": 0.76,
        "country": "Thailand",
        "currency": "THB",
        "forecast": 0.8,
        "name": "Core CPI (YoY) (Jul)",
        "previous": 0.8,
        "timestamp": 1470022200,
        "volatility": 0
    },
    {
        "actual": 0.1,
        "country": "Thailand",
        "currency": "THB",
        "forecast": 0.45,
        "name": "CPI (YoY) (Jul)",
        "previous": 0.38,
        "timestamp": 1470022200,
        "volatility": 1
    },
    {
        "actual": 3.49,
        "country": "Indonesia",
        "currency": "IDR",
        "forecast": 3.59,
        "name": "Core Inflation (YoY) (Jul)",
        "previous": 3.49,
        "timestamp": 1470024000,
        "volatility": 1
    },
    {
        "actual": 0.78,
        "country": "Indonesia",
        "currency": "IDR",
        "name": "Foreign Tourism (Jun)",
        "previous": 11.99,
        "timestamp": 1470024000,
        "volatility": 0
    },
    {
        "actual": 3.21,
        "country": "Indonesia",
        "currency": "IDR",
        "forecast": 3.37,
        "name": "Inflation (YoY) (Jul)",
        "previous": 3.45,
        "timestamp": 1470024000,
        "volatility": 0
    },
    {
        "actual": 0.69,
        "country": "Indonesia",
        "currency": "IDR",
        "forecast": 0.85,
        "name": "Inflation (MoM) (Jul)",
        "previous": 0.66,
        "timestamp": 1470024000,
        "volatility": 1
    },
    {
        "actual": 51.8,
        "country": "India",
        "currency": "INR",
        "name": "Nikkei Markit Manufacturing PMI (Jul)",
        "previous": 51.7,
        "timestamp": 1470027600,
        "volatility": 0
    },
    {
        "actual": -4.6,
        "country": "Estonia",
        "currency": "EUR",
        "name": "Estonian Industrial Production (YoY) (Jun)",
        "previous": -2.0,
        "timestamp": 1470027600,
        "volatility": 0
    },
    {
        "actual": -3.1,
        "country": "Estonia",
        "currency": "EUR",
        "name": "Estonian Industrial Production (MoM) (Jun)",
        "previous": -3.3,
        "timestamp": 1470027600,
        "volatility": 0
    },
    {
        "actual": 0.08,
        "country": "Peru",
        "currency": "PEN",
        "forecast": 0.21,
        "name": "CPI (MoM) (Jul)",
        "previous": 0.14,
        "timestamp": 1470027600,
        "volatility": 0
    },
    {
        "actual": 49.5,
        "country": "Russia",
        "currency": "RUB",
        "name": "Markit Manufacturing PMI (Jul)",
        "previous": 51.5,
        "timestamp": 1470031200,
        "volatility": 1
    },
    {
        "actual": 55.4,
        "country": "Sweden",
        "currency": "SEK",
        "forecast": 51.6,
        "name": "Manufacturing PMI (Jul)",
        "previous": 53.0,
        "timestamp": 1470033000,
        "volatility": 0
    },
    {
        "actual": 50.3,
        "country": "Poland",
        "currency": "PLN",
        "forecast": 51.6,
        "name": "Manufacturing PMI (Jul)",
        "previous": 51.8,
        "timestamp": 1470034800,
        "volatility": 0
    },
    {
        "actual": 321.3,
        "country": "Austria",
        "currency": "EUR",
        "name": "Austrian Unemployment Change (Jul)",
        "previous": 320.0,
        "timestamp": 1470034800,
        "volatility": 0
    },
    {
        "actual": 8.0,
        "country": "Austria",
        "currency": "EUR",
        "name": "Austrian Unemployment Rate (Jul)",
        "previous": 8.1,
        "timestamp": 1470034800,
        "volatility": 0
    },
    {
        "actual": 54.8,
        "country": "Norway",
        "currency": "NOK",
        "forecast": 51.5,
        "name": "Manufacturing PMI (Jul)",
        "previous": 53.8,
        "timestamp": 1470034800,
        "volatility": 0
    },
    {
        "actual": 47.6,
        "country": "Turkey",
        "currency": "TRY",
        "name": "Manufacturing PMI (Jul)",
        "previous": 47.4,
        "timestamp": 1470034800,
        "volatility": 0
    },
    {
        "actual": 53.9,
        "country": "Hungary",
        "currency": "HUF",
        "name": "Manufacturing PMI (Jul)",
        "previous": 50.9,
        "timestamp": 1470034800,
        "volatility": 0
    },
    {
        "actual": 1.1,
        "country": "Mauritius",
        "currency": "MUR",
        "name": "CPI (YoY) (Jul)",
        "previous": 1.1,
        "timestamp": 1470034800,
        "volatility": 0
    },
    {
        "actual": 51.0,
        "country": "Spain",
        "currency": "EUR",
        "forecast": 51.6,
        "name": "Spanish Manufacturing PMI (Jul)",
        "previous": 52.2,
        "timestamp": 1470035700,
        "volatility": 1
    },
    {
        "actual": 49.3,
        "country": "Czech Republic",
        "currency": "CZK",
        "forecast": 52.1,
        "name": "Markit PMI (Jul)",
        "previous": 51.8,
        "timestamp": 1470036600,
        "volatility": 0
    },
    {
        "actual": 51.2,
        "country": "Italy",
        "currency": "EUR",
        "forecast": 52.0,
        "name": "Italian Manufacturing PMI (Jul)",
        "previous": 53.5,
        "timestamp": 1470037500,
        "volatility": 1
    },
    {
        "actual": 48.6,
        "country": "France",
        "currency": "EUR",
        "forecast": 48.6,
        "name": "French Manufacturing PMI (Jul)",
        "previous": 48.6,
        "timestamp": 1470037800,
        "volatility": 1
    },
    {
        "actual": 53.8,
        "country": "Germany",
        "currency": "EUR",
        "forecast": 53.7,
        "name": "German Manufacturing PMI (Jul)",
        "previous": 53.7,
        "timestamp": 1470038100,
        "volatility": 2
    },
    {
        "actual": 48.7,
        "country": "Greece",
        "currency": "EUR",
        "name": "Greek Manufacturing PMI (Jul)",
        "previous": 50.4,
        "timestamp": 1470038400,
        "volatility": 0
    },
    {
        "actual": 8.78,
        "country": "Turkey",
        "currency": "TRY",
        "name": "Exports (Jul)",
        "previous": 11.87,
        "timestamp": 1470038400,
        "volatility": 0
    },
    {
        "actual": 52.0,
        "country": "Euro Zone",
        "currency": "EUR",
        "forecast": 51.9,
        "name": "Manufacturing PMI (Jul)",
        "previous": 51.9,
        "timestamp": 1470038400,
        "volatility": 1
    },
    {
        "actual": 48.2,
        "country": "United Kingdom",
        "currency": "GBP",
        "forecast": 49.1,
        "name": "Manufacturing PMI (Jul)",
        "previous": 49.1,
        "timestamp": 1470040200,
        "volatility": 2
    },
    {
        "actual": 52.5,
        "country": "South Africa",
        "currency": "ZAR",
        "name": "Manufacturing PMI",
        "previous": 53.7,
        "timestamp": 1470042000,
        "volatility": 0
    },
    {
        "actual": -0.63,
        "country": "Netherlands",
        "currency": "EUR",
        "name": "Dutch 3-Month T-bill Auction",
        "previous": -0.606,
        "timestamp": 1470044700,
        "volatility": 0
    },
    {
        "actual": -0.608,
        "country": "Netherlands",
        "currency": "EUR",
        "name": "Dutch 6-Month T-bill Auction",
        "previous": -0.597,
        "timestamp": 1470044700,
        "volatility": 0
    },
    {
        "actual": 44.88,
        "country": "South Africa",
        "currency": "ZAR",
        "name": "Total Vehicle Sales (Jul)",
        "previous": 44.94,
        "timestamp": 1470051000,
        "volatility": 0
    },
    {
        "actual": -17.0,
        "country": "South Africa",
        "currency": "ZAR",
        "name": "Total Vehicle Sales (YoY) (Jul)",
        "previous": -10.6,
        "timestamp": 1470051000,
        "volatility": 0
    },
    {
        "actual": 75.63,
        "country": "Czech Republic",
        "currency": "CZK",
        "name": "Budget Balance (Jul)",
        "previous": 40.65,
        "timestamp": 1470052800,
        "volatility": 0
    },
    {
        "actual": -0.56,
        "country": "France",
        "currency": "EUR",
        "name": "French 12-Month BTF Auction",
        "previous": -0.546,
        "timestamp": 1470056400,
        "volatility": 0
    },
    {
        "actual": -0.57,
        "country": "France",
        "currency": "EUR",
        "name": "French 3-Month BTF Auction",
        "previous": -0.572,
        "timestamp": 1470056400,
        "volatility": 0
    },
    {
        "actual": -0.556,
        "country": "France",
        "currency": "EUR",
        "name": "French 6-Month BTF Auction",
        "previous": -0.555,
        "timestamp": 1470056400,
        "volatility": 0
    },
    {
        "actual": 46.0,
        "country": "Brazil",
        "currency": "BRL",
        "forecast": 46.5,
        "name": "Markit Manufacturing PMI (Jul)",
        "previous": 43.2,
        "timestamp": 1470056400,
        "volatility": 0
    },
    {
        "actual": 52.9,
        "country": "United States",
        "currency": "USD",
        "forecast": 52.9,
        "name": "Manufacturing PMI (Jul)",
        "previous": 52.9,
        "timestamp": 1470059100,
        "volatility": 1
    },
    {
        "actual": -0.6,
        "country": "United States",
        "currency": "USD",
        "forecast": 0.5,
        "name": "Construction Spending (MoM) (Jun)",
        "previous": -0.1,
        "timestamp": 1470060000,
        "volatility": 0
    },
    {
        "actual": 49.4,
        "country": "United States",
        "currency": "USD",
        "forecast": 50.3,
        "name": "ISM Manufacturing Employment (Jul)",
        "previous": 50.4,
        "timestamp": 1470060000,
        "volatility": 1
    },
    {
        "actual": 56.9,
        "country": "United States",
        "currency": "USD",
        "name": "ISM Manufacturing New Orders Index (Jul)",
        "previous": 57.0,
        "timestamp": 1470060000,
        "volatility": 0
    },
    {
        "actual": 52.6,
        "country": "United States",
        "currency": "USD",
        "forecast": 53.0,
        "name": "ISM Manufacturing PMI (Jul)",
        "previous": 53.2,
        "timestamp": 1470060000,
        "volatility": 2
    },
    {
        "actual": 55.0,
        "country": "United States",
        "currency": "USD",
        "forecast": 60.0,
        "name": "ISM Manufacturing Prices (Jul)",
        "previous": 60.5,
        "timestamp": 1470060000,
        "volatility": 0
    },
    {
        "actual": 50.6,
        "country": "Mexico",
        "currency": "MXN",
        "forecast": 51.0,
        "name": "Manufacturing PMI (Jul)",
        "previous": 51.1,
        "timestamp": 1470061800,
        "volatility": 0
    },
    {
        "actual": 0.285,
        "country": "United States",
        "currency": "USD",
        "name": "3-Month Bill Auction",
        "previous": 0.32,
        "timestamp": 1470065400,
        "volatility": 0
    },
    {
        "actual": 0.395,
        "country": "United States",
        "currency": "USD",
        "name": "6-Month Bill Auction",
        "previous": 0.425,
        "timestamp": 1470065400,
        "volatility": 0
    },
    {
        "actual": 4.58,
        "country": "Brazil",
        "currency": "BRL",
        "forecast": 4.95,
        "name": "Trade Balance (Jul)",
        "previous": 3.97,
        "timestamp": 1470074400,
        "volatility": 0
    },
    {
        "actual": 180.09,
        "country": "Argentina",
        "currency": "ARS",
        "forecast": 181.3,
        "name": "Tax Revenue (Jul)",
        "previous": 174.6,
        "timestamp": 1470085200,
        "volatility": 0
    },
    {
        "actual": 0.1,
        "country": "South Korea",
        "currency": "KRW",
        "forecast": 0.2,
        "name": "CPI (MoM) (Jul)",
        "previous": 0.0,
        "timestamp": 1470092400,
        "volatility": 0
    },
    {
        "actual": 0.7,
        "country": "South Korea",
        "currency": "KRW",
        "forecast": 0.8,
        "name": "CPI (YoY) (Jul)",
        "previous": 0.8,
        "timestamp": 1470092400,
        "volatility": 1
    },
    {
        "actual": 24.7,
        "country": "Japan",
        "currency": "JPY",
        "forecast": 24.3,
        "name": "Monetary Base (YoY)",
        "previous": 25.4,
        "timestamp": 1470095400,
        "volatility": 0
    }
]
